{
  "1": {
    "ブロンズクラス": ""
  },
  "2": {
    "シルバークラス": ""
  },
  "3": {
    "ゴールデンクラス": ""
  },
  "4": {
    "clarity_nt_char_4": "clarity_nt_char_4"
  },
  "5": {
    "プラチナクラス": ""
  },
  "6": {
    "こうげきセット": ""
  },
  "7": {
    "ロイヤルクラス": ""
  },
  "8": {
    "海魔の眼甲セット": ""
  },
  "9": {
    "clarity_nt_char_9": "clarity_nt_char_9"
  },
  "10": {
    "ねこひげセット": ""
  },
  "11": {
    "モノクルセット": ""
  },
  "12": {
    "ブロンズジュエル": ""
  },
  "13": {
    "clarity_nt_char_13": "clarity_nt_char_13"
  },
  "14": {
    "オータムジュエル": ""
  },
  "15": {
    "clarity_nt_char_15": "clarity_nt_char_15"
  },
  "16": {
    "スプリング★ナイト": ""
  },
  "17": {
    "サマー★ナイト": ""
  },
  "18": {
    "オータム★ナイト": ""
  },
  "19": {
    "clarity_nt_char_19": "clarity_nt_char_19"
  },
  "20": {
    "シルバージュエル": ""
  },
  "21": {
    "clarity_nt_char_21": "clarity_nt_char_21"
  },
  "22": {
    "ゴールデンジュエル": ""
  },
  "23": {
    "ウィンター★ナイト": ""
  },
  "24": {
    "ぼうぎょセット": ""
  },
  "25": {
    "スプリングジュエル": ""
  },
  "26": {
    "かいふくセット": ""
  },
  "27": {
    "さいだいＨＰセット": ""
  },
  "28": {
    "こうげき魔力セット": ""
  },
  "29": {
    "黒アイパッチセット": ""
  },
  "30": {
    "白アイパッチセット": ""
  },
  "31": {
    "期間限定★ナイトフェス": ""
  },
  "32": {
    "かいとうの仮面セット": ""
  },
  "33": {
    "clarity_nt_char_33": "clarity_nt_char_33"
  },
  "34": {
    "ウィンタージュエル": ""
  },
  "35": {
    "サマージュエル": ""
  },
  "36": {
    "ロイヤルジュエル": ""
  },
  "37": {
    "clarity_nt_char_37": "clarity_nt_char_37"
  },
  "38": {
    "アクセルギアセット": ""
  },
  "39": {
    "教授のメガネセット": ""
  },
  "40": {
    "プラチナジュエル": ""
  }
}