{
    "1": {
        "「キャハハハハッ！！": "Cahahahahaha!"
    },
    "2": {
        "「たとえ　すべての麦を倒し|　水が干上がり　涙が枯れても……": "Even if it kills all the wheat| And when the water dries up and the tears run dry"
    },
    "3": {
        "「メルサンディ村が　滅びぬ限り|　私の恨みは　止まらない。": "As long as the village of Mersandi remains|intact, my resentment will continue..."
    },
    "4": {
        "「……永遠の夜とともに|　魔女グレイツェル　参りました<heart>": " With the eternal night| Witch Grätzel, I'm here<heart>"
    },
    "5": {
        "「コケコッコーーーーー！": "Cock-a-doodle-doo!"
    },
    "6": {
        "「コケコッコーーーーー！！": "Cock-a-doodle-doo!"
    },
    "7": {
        "「コケコッコーーーーー！！！": "Cock-a-doodle-doo!"
    },
    "8": {
        "「コ　コケ……。": "Koke..."
    },
    "9": {
        "「フフ……<heart>|　私の弱点が　ニワトリだって|　思ったみたいね。": "Huh<heart>You'd think my weakness would be chickens,|but..."
    },
    "10": {
        "「そういえば　前に　ニワトリの声を聞いて|　逃げたことがあったかしら？": "Come to think of it, have you ever heard|chickens before and run away?"
    },
    "11": {
        "「ざんね～ん……。|　逃げたのは　朝の光が　苦手だからッ<heart>": "Sorry... I ran away because I don't like the|morning light.<heart>"
    },
    "12": {
        "「でも　今は　魔法で　黒い雲を呼んでるし|　弱点でも　なんでもないのだけど。": "But right now, I'm magically calling up a|black cloud, and it's not a weakness or|anything..."
    },
    "13": {
        "「ねえ　旅人さん<heart>|　あなたも　パンになっちゃう？": "Hey, traveler<heart>Do you want to become bread?"
    },
    "14": {
        "「パンのように　焼きあがるのは|　テメーのほうだぜ。": "The only thing that bakes like bread is|your..."
    },
    "15": {
        "「俺に　なんの恨みがあるか知らねえが|　これ以上　村に手を出すな。": "I don't know what it is you want from me, but|if you do anything more to this village..."
    },
    "16": {
        "「あらん　会いたかったわ。|　ザンクローネッ<heart>": "Oh, my God. I've missed you... Zanklonet.<heart>"
    },
    "17": {
        "「あんたは　俺の身体をバラバラにした上|　その身体を使って　俺の村を襲いやがった。|　怒りで　ハラワタが焦げそうだぜ。": "You dismembered me, and then you used my body|to attack my village. I'm so angry, my guts|are burning."
    },
    "18": {
        "「いやあね。自分の罪を　棚に上げて|　私を　責めるなんて……": "I... I can't believe you're blaming me for|your own sins."
    },
    "19": {
        "「ホント　身も心も　ちっちゃいオトコ<heart>": "I'm really a little guy, inside and out<heart>"
    },
    "20": {
        "「罪……だと……？": "Sin... What the...?"
    },
    "21": {
        "「あなたの　罪のせいで|　メルサンディ村は　滅んじゃうのよ。|　たいした英雄さんね<heart>": "Because of your sins, the village of Melsundy|perished... You're a hero.<heart>"
    },
    "22": {
        "「また　会いにきてね　ザンクローネ。|　何度でも　会いにきて……<heart>": "Come see me again, Zank... Come again and|again...<heart>"
    },
    "23": {
        "「……その時こそ　あなたの大切なものを |　何もかも　グッチャグチャにしてあげる。": "... And that's when I'm going to make sure|that everything you hold dear gets torn|apart..."
    },
    "24": {
        "<if_woman>「さあ　お嬢さん。お家に帰って|　滅びの恐怖を　伝えてくれるかしら。<else>「さあ　坊や。お家に帰って|　滅びの恐怖を　伝えてくれるかしら。<endif>": "<if_woman>Now... Go home and tell me your fear of|perdition...<else>Now... Go home and tell me your fear of|perdition...<endif>"
    },
    "25": {
        "「キャハハハハッ！！": "Cahahahahaha!"
    },
    "26": {
        "<pc>は　こもれびの広場の井戸の周りで|コッケちゃんを　解き放った！": "<pc> has unleashed a cockerel around the well in|Komorebi no Hiroba!"
    }
}