{
  "1": {
    "「待たせたな。来たぜ～　ガウラド。": "Wait... Here it comes!"
  },
  "2": {
    "「<cs_pchero>殿も　来たのですか。|　いいでしょう。歓迎いたしますよ。": "<cs_pchero>You're here... Good... You are welcome..."
  },
  "3": {
    "「で　なんの用なんだ？|　お小言なら　もう聞きたくないぜ。|　マジメに　やってるだろ　オレ。": "So what do you want? I don't want to hear|another word about... I'm serious. I'm|serious."
  },
  "4": {
    "「お別れです　ヤーン様。": "Goodbye. Ya..."
  },
  "5": {
    "「は？　何を言ってるんだ　ガウラド。": "Huh? What are you talking about, Ga..."
  },
  "6": {
    "「超天道士の名を持つ者と|　やっと　闘える日が来ました。": ""
  },
  "7": {
    "「私が　あなたを殺します。": "I killed you..."
  },
  "8": {
    "「おいおい。お前の　じょうだんは|　相変わらず　つまんねえなあ。|　もっと　笑えるのにしろよ。": "Oh... Your jokes are as boring as ever... It|could be so much funnier..."
  },
  "9": {
    "「超天道士を名乗る者を殺し|　その名に宿りし　チカラを得る……。|　それが　この私の使命……。": "I will kill those who claim to be|supernaturalists and gain the power that|resides in their names. That is my mission..."
  },
  "10": {
    "「お前……。": "You..."
  },
  "11": {
    "<pipipi_mid>「超天道士を倒すため　魔界より訪れた使者。|　武闘魔ガウラド……それが　私の本当の姿だ。": "<pipipi_mid>From the demon world to defeat the|supernatural masters... The martial arts|demon Gaurad... That's what I really am..."
  },
  "12": {
    "「だが　なんということか……。|　私が目的を果たさんとしたとき　超天道士は|　病に冒され　死を目前としていたのだ。": "But what a surprise. Just as I was about to|accomplish my goal, the supernaturalist was|stricken with an illness and on the verge of|<br>|death."
  },
  "13": {
    "「そんな　おとろえた超天道士を倒しても|　チカラを得ることなど　できぬ！|　私が倒すのは　完全なる超天道士でなくてはっ！": "I can't gain power by defeating such a mute|supernaturalist! I will only defeat a perfect|supernaturalist!"
  },
  "14": {
    "「だから　待ったのだ。|　超天道士の名を継ぐ者が現れる　その日を！|　貴様を倒せば　私の使命は果たされるのだ！！": "So, I'm waiting... For the day when the heir|to the Supertemptress name appears! If I|defeat you, my mission will be fulfilled!"
  },
  "15": {
    "「くだらねえ……。|　そんなことのために　お前は　これまで|　オレの世話をしてきたっていうのか？": "Nonsense... Is that why you've been taking|care of me all this time?"
  },
  "16": {
    "「ヤーン！　超天道士の名を継ぐ者よ！|　さあ　私と闘え！|　そして　そのチカラをよこせ！": "Yarn! Heir to the name of the|supernaturalist! Fight me now! And give me|your power!"
  },
  "17": {
    "「イヤだね。オレは　お前の相手なんか|　これっぽっちも　する気ね～よ。": "I... I don't want to deal with you, not even|a little."
  },
  "18": {
    "「超天道士の名を継ぐ者が　逃げるのか！？": ""
  },
  "19": {
    "「ちげ～っつーの。お前なんかじゃ|　オレの相手にならね～って　言ってるんだよ。": "Damn it... I'm saying you're no match for|me..."
  },
  "20": {
    "「……そうだな。コイツに勝てたら|　お前の相手をしてやっても　いいぜ。": "... I... If you can beat this guy, I'll let|you play with him."
  },
  "21": {
    "「<cs_pchero>　悪いが頼むぜ。|　アンタの闘いを　見せてやってくれよ。": "<cs_pchero>I'm sorry, but... I just wanted to show you|what you're made of."
  },
  "22": {
    "「ガウラド。お前じゃ　<cs_pchero>を|　倒すなんて　できね～と思うぜ。": "Ga... It's you.<cs_pchero>You can't defeat the..."
  },
  "23": {
    "「<cs_pchero>を倒せば　貴様が|　この私と闘うと　いうのだな……。|　その言葉に　いつわりはないな？": "<cs_pchero>So you're willing to fight me if I defeat...|Is there any doubt in your mind?"
  },
  "24": {
    "「<cs_pchero>よ。まずは貴様からだ。|　さあ　私の使命のため　消えるがいい！！": "<cs_pchero>I'll tell you what. First you... Now, for the|sake of my mission, you will disappear!"
  },
  "25": {
    "「まさか……。超天道士の名を持たぬ者に|　この私が　敗れる……だと！？　": "No way... I will be defeated by someone who|doesn't have the name of the|supernaturalist... What?"
  },
  "26": {
    "「名前に　チカラが宿るわけじゃない。|　お前がしてることには　なんの意味もね～よ。": "Your name doesn't mean anything. What you're|doing doesn't mean anything..."
  },
  "27": {
    "「超天道士の名なんか　継いでなくても|　<cs_pchero>は　こんだけ　強いんだぜ。": "Even if I didn't inherit the name of the supernaturalist|<cs_pchero>He's so strong..."
  },
  "28": {
    "「だが　私は　超天道士を倒さねば……。|　使命を果たさねば　魔界へ帰ることはできぬ！": "But I have to defeat the supernaturalists. If|I don't complete my mission, I can't return|to the demon world!"
  },
  "29": {
    "「私と……。私と闘え　ヤーン！！": "Fight me... Fight me, Jahn!"
  },
  "30": {
    "「わかった。オレが相手をしてやる。": "I... I'll take care of..."
  },
  "31": {
    "「フフ……。なんという強さ……。|　さすが　超天……道士……の……。": "Huh... What strength... As expected of a|supreme... Daoist... of..."
  },
  "32": {
    "「なあ　ガウラド……。オレと　お前はさ。|　ずいぶん長く　一緒に暮らしてたよな。|　わがままも　たくさん　言ったっけなあ……。": "Hey, Gaurad... Me and you... We lived|together for a long time... I've said a lot|of selfish things..."
  },
  "33": {
    "「じ～さんが死んだ後も　お前がオレの世話を|　焼いてくれたのは　そんな　くだらない|　使命のためだけじゃ　なかったんだろ？": "It wasn't just for such a trivial mission|that you took care of me after my grandpa|died, was it?"
  },
  "34": {
    "「なのに　なぜ　いつまでも|　そんな使命に　こだわってさ……。|　こんなことをしたんだよ……。　": "So why are you so obsessed with this mission?|I've done this..."
  },
  "35": {
    "「貴様には　わかるまい……。|　魔界に生きる者に　課せられた使命の重さを。": "You have no idea... The mission of those who|live in the demon world..."
  },
  "36": {
    "「だが……。だが　なぜ私は|　その使命を果たさねば　ならなかったのか……。|　今となっては　もう覚えておらぬ……。": "But... But I don't know why I had to do it. I|can't remember now."
  },
  "37": {
    "「いつからか　私は　理由もなく|　ただ　与えられた使命を果たすためだけに|　生きてきたように思える……。": "For some reason, it seems like I've been|living my life for no reason, just to fulfill|the mission I've been given."
  },
  "38": {
    "「……使命のことは　もう忘れちまえ。|　そして　ゆっくり眠れば　いいさ。": "... I'll forget about the mission. And|sleep..."
  },
  "39": {
    "「せめて　最期は……。あなたの知る姿で……。": "At least in the end... In a way that you|know..."
  },
  "40": {
    "「私は　使命を果たすことに囚われ……。|　安息の日など　一日たりとも|　訪れることはなかった……。": "I was so caught up in fulfilling my|mission... I never had a day of rest..."
  },
  "41": {
    "「ただ……なぜか……|　あなたと共に暮らした日々は……。": "It's just... For some reason... The days that|I lived with you..."
  },
  "42": {
    "「とても　楽しかっ……た……。": "It was so much fun... It was..."
  },
  "43": {
    "「ヤーン……様……。": "Jahn... I'm sorry..."
  },
  "44": {
    "「…………。": "..."
  },
  "45": {
    "「中に　コレが入ってたよ。|　武闘家の証……って　言われてるヤツだ。": "Inside, you'll find this... It's a sign of a|martial artist... They say..."
  },
  "46": {
    "「超天道士が死ぬ間際に　オレに渡せと言って|　ガウラドのヤツに　あずけたらしいぜ。|　この手紙に　そう書いてあったよ……。": "When the supernaturalist was dying, he asked|me to give it to him... so I gave it to|Gaurav. That's what it said in this letter."
  },
  "47": {
    "「大事に　持ってやがったんだなあ。|　アイツの使命とは　関係ないモノだろうに。": "He's been holding on to it. It had nothing to|do with his mission."
  },
  "48": {
    "「……なあ　<cs_pchero>。|　突然だけどさ。オレと勝負してくれよ。|　確かめたいことが　あるんだ。": " Hey<cs_pchero>I'm sorry. All of a sudden... I want you to|play with me. There's something I want to|make sure of..."
  },
  "49": {
    "「アンタと拳を交えれば　きっと|　その答えが　わかるはずなんだよ。": "I'm sure I can find the answer to that|question when I come face to face with you."
  },
  "50": {
    "「本格的に　コロシアムで　やろうぜ。|　そこの関係者の　グララってオーガの女に|　もう　話をつけてあるんだ。": "We're going to have to do this in earnest at|the Coliseum. I've already spoken to one of|their officials, an Ogre woman named Grala..."
  },
  "51": {
    "「オレは　ジュレットの町に　ヤボ用がある。|　アンタは　先に　ラッカラン島の|　コロシアムに　行っててくれないか。": "I'm off to the town of Juliet. You're gonna|have to go to the Coliseum on Lackalang|Island first."
  },
  "52": {
    "「<cs_pchero>　今度は　イケるよな。|　これまでの修行を　思いだせばいいんだ。|　アンタなら　勝てるはずだぜ。": "<cs_pchero>This time... Just remember what you've|learned so far. I know you can do it."
  },
  "53": {
    "「ヤーン。まだ貴様は　闘おうとしないのか？|　私の使命は　超天道士の名を持つ貴様を|　倒さぬ限り　果たされぬのだ！": "... You still don't want to fight? My mission|will not be accomplished until I defeat you|in the name of the supernaturalists!"
  },
  "54": {
    "「<cs_pchero>は　まだ　負けてね～よ。|　お前の前で　倒れてるか？|　立ちあがって　闘おうとしてるだろ？": "<cs_pchero>I'm still losing... Is he lying there in|front of you? Isn't he trying to get up and|fight?"
  },
  "55": {
    "「……相変わらず　クチの減らない男だ。|　よかろう。ならば　今度は完全に|　たたきつぶしてくれるわっ！": "... I'm still getting the same complaints...|No... Now you're going to crush me|completely!"
  },
  "56": {
    "「よく来てくれた～　<cs_pchero>。|　ここなら　ジャマも入らないだろ？": "Thank you for coming<cs_pchero>I'm sorry. You won't get in trouble here,|will you?"
  },
  "57": {
    "「アンタと　拳を交えれば|　オレが確かめたいことの　答えが出るんだ。|　だから　手加減とかは　ナシにしてくれよ。": "If I could just get my hands on you, I'd have|the answer to everything I want to know. So|let's not go easy on each other."
  },
  "58": {
    "「……もう　言葉は　いらないよな。|　あとは　拳で語り合おうぜ。": "I don't... No more words. We can talk with|our fists."
  },
  "59": {
    "「いくぞ～　<cs_pchero>！": "Here we go!<cs_pchero>！"
  },
  "60": {
    "「<cs_pchero>……。アンタなら|　また来てくれると　思ってたぜ～。": "<cs_pchero>I thought... I was hoping you'd come back."
  },
  "61": {
    "「勝負は　まだ　ついてないよな？|　<pc>の本気を　オレは|　まだ　見せてもらってないぜ～。": "The game's not over yet, is it?<pc> I've yet to be shown the true nature of..."
  },
  "62": {
    "「今度は　見せてくれよ～。|　<cs_pchero>の　本気の拳をな！！": "Now, let me see...<cs_pchero>I've got a real fist!"
  },
  "63": {
    "「ははっ　強いなあ～　<cs_pchero>。|　超天道士の名を継いだオレが　負けちまったよ。": ""
  },
  "64": {
    "「だが　ずっと　確かめたかったことが|　アンタと闘って　やっと　わかった。|　それが　なんなのか　聞いてくれるか。": "But there's something I've been wanting to|find out for a long time, and now that I've|fought you... Ask me what it is..."
  },
  "65": {
    "「……オレが　じ～さんに弟子入りしたのは|　超天道士って名が　欲しかったからじゃない。|　その強さに　あこがれたからだ。": "... I apprenticed myself to my grandfather|because I wanted to be called a|supernaturalist. I admired his strength..."
  },
  "66": {
    "「その名を継がなくても　超天道士を超える強さを|　身につけられると　オレは信じていた。": "I believe that even if I don't carry that|name, I can become even more powerful than|the supernaturalists."
  },
  "67": {
    "「だから　ずっと　名を継ぐことを避けてたのさ。|　本気のじ～さんと闘って　勝つ日が来るまで|　……と思ってな。": "That's why I've always avoided taking over|the name... Until the day I fight my real|father and win... I thought..."
  },
  "68": {
    "「なのに　じ～さんは　死んじまった……。": "And now he's dead..."
  },
  "69": {
    "「……本当はさ。超天道士の名を継いだ|　アンタと闘って　勝つつもりだったんだ。|　それが　逆になっちまったってわけさ。": "... The book... I was going to fight you, the|heir to the Supernatural Order, and win. But|it turned out the other way around..."
  },
  "70": {
    "「だが　超天道士の名を継いだ　このオレを|　アンタが　超えてみせてくれた。": "But I'm the heir to the Supernatural name,|and you must surpass me."
  },
  "71": {
    "「名前が強さを　もたらすわけじゃない。|　強さってのは　人に宿るってことが|　やっと　確かめられたよ……。": "It's not the name that gives you strength.|It's finally confirmed to me that strength|resides in people..."
  },
  "72": {
    "「よし……っと。|　<cs_pchero>のおかげで|　いろいろと　ふっきれたぜ。": "Okay. .....<cs_pchero>Thanks to you, I'm feeling a lot better."
  },
  "73": {
    "「超天道士の名は　今やオレの身体の一部だ。|　この名と共に　オレは生きていくよ。": "The name of the supernaturalist is now my|body. With this name, I live."
  },
  "74": {
    "「<cs_pchero>～！|　アンタとの勝負は　本当に楽しかったぜ。": "<cs_pchero>～Oh! It's going to be so much easier playing|with you..."
  },
  "75": {
    "「アンタは　いい武闘家になるよ。|　超天道士のように　伝説に名を残す|　そんな　すげえ武闘家だ。": "You'd make a great fighter... You're going to|go down in history as one of the greats..."
  },
  "76": {
    "「このオレが　言うんだ。|　絶対に　まちがいね～って！": "I'm the one who said... I'm sure you're|right."
  },
  "77": {
    "「オレに勝ったんだからな。|　コレは　アンタに受け取ってほしい。|　ガウラドの置いていった　武闘家の証だ。": "You beat me. This is for you. Gaurad left it|to me."
  },
  "78": {
    "「その武闘家の証は　いつか　オレが|　証に　ふさわしい男になる日まで|　アンタに　あずけておくよ。": "I'll leave the proof of your martial prowess|to you until the day I become a man worthy of|it."
  },
  "79": {
    "「勝者への　ごほうびだ。|　コレを　アンタに贈らせてもらおう。": "To the victor... I'd like to present this to|you..."
  },
  "80": {
    "「オレも　超天道士の名に恥じない|　武闘家にならなきゃ　いけね～からな。|　もっと　修行に　はげむことにする。": "I must become a martial artist worthy of the|name \"Choutendouji\"... I must train harder..."
  },
  "81": {
    "「今度　闘うことがあったら　絶対に負けないぜ。|　超天道士の名に　かけてな！": "If I ever have to fight again, I'll never|lose. In the name of the supernaturalist!"
  },
  "82": {
    "「じゃあ　またな　<cs_pchero>！": "I'll see you later<cs_pchero>！"
  },
  "83": {
    "「…………。": "..."
  }
}