{
    "1": {
        "「おおっ　<cs_pchero>。|　ついに　にっくき魔女ハバネロを|　倒してくれたカボね！": "Whoa!<cs_pchero>You've finally defeated the Habanero! You|finally defeated the evil witch Habanero,|Cabo!"
    },
    "2": {
        "「ぎゃ～～～！|　まだ　生きてるカボ～～～！！": "Oh, no! He's still alive!"
    },
    "3": {
        "「まさか……。ママうえさま！？": "No way... Mama Uesama?"
    },
    "4": {
        "「……ううっ。ジャッ……ク？": "...... Jack... Qu?"
    },
    "5": {
        "「ママうえさま　しっかりカボ。|　いったい　何が　あったのカボ？": "Mama Superior, I'm so sorry... What the hell|happened to you, Cabo?"
    },
    "6": {
        "「私は　何者かに呪いで　魔女ハバネロに|　姿を変えられ……　からい刺激を欲するあまり|　この国を　ひどい姿に変えてしまった……。": "I was cursed by someone to be a habanero|witch. I have transformed this country into a|horrible mess..."
    },
    "7": {
        "「……ありがとう。私は　甘党の魔女シュガー。|　あなたには　お礼をしたいところですが|　まずは　この国を　元に戻さなければ……。": "... I am... I'm a witch with a sweet tooth.|I'd like to thank you, but first, I have to|get this country back on track."
    },
    "8": {
        "「ママうえさまっ　すごいカボ。|　スウィ～ツランドが　元通りになったカボ。|　また　甘いお菓子が　食べれるカボよ！": "Mom, you're amazing... Sweetland is back to|normal... We'll have sweet treats again,|Cabo!"
    },
    "9": {
        "「これも全部　<cs_pchero>が|　がんばってくれた　おかげカボね。|　お礼を　受け取ってほしいカボ！": "And all this<cs_pchero>I want you to take this. I want you to accept|my thanks, Cabo!"
    },
    "10": {
        "「<cs_pchero>が　来てくれなければ|　この国は　どうなっていたことか。|　本当に　ありがとうございました。": "<cs_pchero>If you hadn't come, I don't know where this|country would be. Thank you so much..."
    },
    "11": {
        "ふふふ……。ふははははははっ！！": "Hmmm... Hahahahahaha!"
    },
    "12": {
        "「我が名は　辛党の神　カプサイ神なり！": "I am the god of spice, the god of capsicum!"
    },
    "13": {
        "「辛党の神……？|　それじゃ　ママうえに　呪いをかけて|　魔女ハバネロにしたのは　お前カボ！？": "God of spice...? So it was you, Cabo, who put|a curse on Mama and turned her into a|habanero witch?"
    },
    "14": {
        "「ふふふ……。いかにも！|　我が呪いが断ち切られるとは　思わなんだが|　これはこれで　心地よいピリ辛な刺激よ。": "Hmmm... Indeed! I didn't think my curse would|be broken, but it's a nice, spicy..."
    },
    "15": {
        "「だが　この程度の刺激では　満足できぬ。|　こうなれば　我自身の手で|　この国を　激辛の国に変えてくれようぞ！": "But I'm not satisfied with this level of|stimulation. I will turn this country into a|hot and spicy land with my own hands!"
    },
    "16": {
        "「このまま　戦いを挑むのは危険です！|　辛党の神を　甘く見ては　いけません。|　一度　退きましょう！！": "It's not safe to fight like this! Don't|underestimate the God of Spicy Taste... Let's|retreat for a moment!"
    },
    "17": {
        "「ふふふ……。それでよい。|　貴様たちの　あがく様を見ながら|　この刺激を　楽しませてもらうとしよう……。": "Mmm-hmm... Well... I'll enjoy the stimulation|as I watch you struggle."
    },
    "18": {
        "「ジャック……。|　私は　この国を元の姿に戻すため|　チカラを　使い果たしてしまいました。": "Jack... I've used up all my energy trying to|restore this country to its former self."
    },
    "19": {
        "「しばらくの間　休まねばなりません。|　後のことは　あなたたちに　まかせます……。": "I'm going to have to rest for a while. I'll|leave the rest to you..."
    },
    "20": {
        "「……<cs_pchero>。ジャックたちに|　あなたのチカラを　貸してあげてください。|　どうか　この国を救っ……て…………。": "<cs_pchero>I'm sorry. I'm asking you to lend your|strength to Jack and the others. Please, save|this country... Please..."
    },
    "21": {
        "「ママうえさま　わかったカボ。|　おいらたちで　カプサイ神の魔の手から|　この国を　守ってみせるカボ！": "Mother Superior, I understand... We will|protect this country from the clutches of the|Kapucai God, Cabo!"
    },
    "22": {
        "「もう一度　キミのチカラを貸してほしいけど|　カプサイ神は　とても　強そうだったカボ。": "I wish I could lend you my strength again,|but the Kappa God seemed so strong..."
    },
    "23": {
        "「だから　おいらは　あいつを倒す手がないか|　ミローレさんに　相談してみるカボよ。|　それが見つかるまで　待ってほしいカボ！": "So I'm gonna talk to Mr. Millore, see if|there's anything we can do to take him|down... You're going to have to wait until I|<br>|find it, Cabo!"
    }
}